bds_sampler/__init__.py
bds_sampler/_sampler.cp37-win_amd64.pyd
bds_sampler/_version.py
bds_sampler-0.1.2.dist-info/LICENSE
bds_sampler-0.1.2.dist-info/METADATA
bds_sampler-0.1.2.dist-info/WHEEL
bds_sampler-0.1.2.dist-info/top_level.txt
bds_sampler-0.1.2.dist-info/RECORD
