Metadata-Version: 2.1
Name: bds-sampler
Version: 0.1.2
Summary: Python bindings for bi-degree sequence generator
Home-page: https://github.com/ianhi/BDS-sampler
Author: Ian Hunt-Isaak
Author-email: ianhuntisaak@gmail.com
License: BSD license
Project-URL: Source Code, https://github.com/ianhi/BDS-sampler
Platform: UNKNOWN
Classifier: Development Status :: 2 - Pre-Alpha
Classifier: License :: OSI Approved :: BSD License
Classifier: Natural Language :: English
Classifier: Programming Language :: Python :: 3
Classifier: Programming Language :: Python :: 3.7
Classifier: Programming Language :: Python :: 3.8
Classifier: Programming Language :: Python :: 3.9
Requires-Python: <3.10,>=3.7
License-File: LICENSE
Requires-Dist: numpy
Requires-Dist: scipy
Provides-Extra: dev
Requires-Dist: ipython ; extra == 'dev'
Requires-Dist: jedi (<0.18.0) ; extra == 'dev'
Requires-Dist: black ; extra == 'dev'
Requires-Dist: flake8 ; extra == 'dev'
Requires-Dist: flake8-docstrings ; extra == 'dev'
Requires-Dist: isort ; extra == 'dev'
Requires-Dist: mypy ; extra == 'dev'
Requires-Dist: pre-commit ; extra == 'dev'
Requires-Dist: pydocstyle ; extra == 'dev'
Requires-Dist: pytest ; extra == 'dev'
Provides-Extra: testing
Requires-Dist: tox ; extra == 'testing'
Requires-Dist: tox-conda ; extra == 'testing'
Requires-Dist: pytest ; extra == 'testing'
Requires-Dist: pytest-cov ; extra == 'testing'
